.coveragerc
LICENSE
MANIFEST.in
README.md
dev_requirements.txt
requirements.txt
setup.cfg
setup.py
versioneer.py
cifsdk/__init__.py
cifsdk/_version.py
cifsdk/cli.py
cifsdk/constants.py
cifsdk/exceptions.py
cifsdk/msg.py
cifsdk/tokens.py
cifsdk.egg-info/PKG-INFO
cifsdk.egg-info/SOURCES.txt
cifsdk.egg-info/dependency_links.txt
cifsdk.egg-info/entry_points.txt
cifsdk.egg-info/requires.txt
cifsdk.egg-info/top_level.txt
cifsdk/client/__init__.py
cifsdk/client/dummy.py
cifsdk/client/http.py
cifsdk/client/ws.py
cifsdk/client/zmq.py
cifsdk/utils/__init__.py
cifsdk/utils/color.py
test/__init__.py
test/test_basics.py
test/test_msgs.py
test/test_tokens.py
test/client/__init__.py
test/client/test_dummy.py
test/client/test_http.py
test/client/test_ws.py
test/client/test_zmq.py