Metadata-Version: 1.1
Name: cifsdk
Version: 4.0
Summary: CIFv4 Python SDK
Home-page: https://github.com/csirtgadgets/verbose-robot-sdk-py
Author: Wes Young
Author-email: wes@csirtgadgets.com
License: MPL2
Keywords: security
Platform: UNKNOWN
Classifier: Topic :: System :: Networking
Classifier: Programming Language :: Python
